mcp_eval/__init__.py
mcp_eval/catalog.py
mcp_eval/config.py
mcp_eval/core.py
mcp_eval/datasets.py
mcp_eval/gen_tests.py
mcp_eval/generation.py
mcp_eval/llm_client.py
mcp_eval/metrics.py
mcp_eval/pytest_plugin.py
mcp_eval/runner.py
mcp_eval/session.py
mcp_eval/tracing_patch.py
mcp_eval/utils.py
mcp_eval/assertions/__init__.py
mcp_eval/assertions/assertions_deprecated.py
mcp_eval/assertions/main.py
mcp_eval/cli/__init__.py
mcp_eval/cli/doctor.py
mcp_eval/cli/generator.py
mcp_eval/cli/issue.py
mcp_eval/cli/list_command.py
mcp_eval/cli/models.py
mcp_eval/cli/utils.py
mcp_eval/cli/validate.py
mcp_eval/evaluators/__init__.py
mcp_eval/evaluators/base.py
mcp_eval/evaluators/equals_expected.py
mcp_eval/evaluators/exact_tool_count.py
mcp_eval/evaluators/is_instance.py
mcp_eval/evaluators/llm_judge.py
mcp_eval/evaluators/max_iterations.py
mcp_eval/evaluators/multi_criteria_judge.py
mcp_eval/evaluators/not_contains.py
mcp_eval/evaluators/path_efficiency.py
mcp_eval/evaluators/response_contains.py
mcp_eval/evaluators/response_time_check.py
mcp_eval/evaluators/shared.py
mcp_eval/evaluators/tool_called_with.py
mcp_eval/evaluators/tool_failed.py
mcp_eval/evaluators/tool_output_matches.py
mcp_eval/evaluators/tool_sequence.py
mcp_eval/evaluators/tool_success_rate.py
mcp_eval/evaluators/tool_was_called.py
mcp_eval/optimizer/README.md
mcp_eval/optimizer/__init__.py
mcp_eval/optimizer/core_trace_process.py
mcp_eval/optimizer/dataloader.py
mcp_eval/optimizer/optimizer_cli.py
mcp_eval/optimizer/predictors.py
mcp_eval/otel/span_tree.py
mcp_eval/report_generation/__init__.py
mcp_eval/report_generation/base.py
mcp_eval/report_generation/console.py
mcp_eval/report_generation/html.py
mcp_eval/report_generation/markdown.py
mcp_eval/report_generation/models.py
mcp_eval/report_generation/report_template.html
mcp_eval/report_generation/summary.py
mcp_eval/report_generation/utils.py
mcp_eval/templates/test_decorators_generated.py.j2
mcp_eval/templates/test_file.py.j2
mcp_unit-0.1.1.dist-info/METADATA
mcp_unit-0.1.1.dist-info/WHEEL
mcp_unit-0.1.1.dist-info/entry_points.txt
mcp_unit-0.1.1.dist-info/licenses/LICENSE
mcp_unit-0.1.1.dist-info/RECORD
